{
  "$schema": "https://json-structure.org/meta/core/v0/#",
  "$id": "https://raw.githubusercontent.com/api-evangelist/amazon-mechanical-turk/refs/heads/main/json-structure/amazon-mechanical-turk-delete-worker-block-request-structure.json",
  "name": "DeleteWorkerBlockRequest",
  "description": "DeleteWorkerBlockRequest schema from Amazon Mechanical Turk API",
  "type": "object",
  "properties": {
    "WorkerId": {
      "allOf": [
        {
          "$ref": "#/components/schemas/CustomerId"
        },
        {
          "description": "The ID of the Worker to unblock."
        }
      ]
    },
    "Reason": {
      "allOf": [
        {
          "$ref": "#/components/schemas/String"
        },
        {
          "description": "A message that explains the reason for unblocking the Worker. The Worker does not see this message."
        }
      ]
    }
  },
  "required": [
    "WorkerId"
  ]
}