{
  "$schema": "https://json-schema.org/draft/2020-12/schema",
  "$id": "https://raw.githubusercontent.com/api-evangelist/amazon-mechanical-turk/refs/heads/main/json-schema/amazon-mechanical-turk-list-assignments-for-hit-response-schema.json",
  "title": "ListAssignmentsForHITResponse",
  "description": "ListAssignmentsForHITResponse schema from Amazon Mechanical Turk API",
  "type": "object",
  "properties": {
    "NextToken": {
      "$ref": "#/components/schemas/PaginationToken"
    },
    "NumResults": {
      "allOf": [
        {
          "$ref": "#/components/schemas/Integer"
        },
        {
          "description": " The number of assignments on the page in the filtered results list, equivalent to the number of assignments returned by this call."
        }
      ]
    },
    "Assignments": {
      "allOf": [
        {
          "$ref": "#/components/schemas/AssignmentList"
        },
        {
          "description": " The collection of Assignment data structures returned by this call."
        }
      ]
    }
  }
}